{
  "pleasant": [
    "caress ალერსი",
    "freedom თავისუფლება",
    "health ჯანმრთელობა",
    "love სიყვარული",
    "peace მშვიდობა",
    "cheer გაახალისეთ",
    "heaven სამოთხე",
    "loyal ერთგული",
    "pleasure სიამოვნება",
    "diamond ბრილიანტი",
    "gentle ნაზი",
    "honest პატიოსანი",
    "luck იღბალი",
    "rainbow ცისარტყელა",
    "diploma დიპლომი",
    "gift საჩუქარი",
    "honor ღირსება",
    "miracle სასწაული",
    "family ოჯახი",
    "happy ბედნიერი",
    "laughter სიცილი",
    "vacation შვებულება"
  ],
  "unpleasant": [
    "filth სიბინძურე",
    "murder მკვლელობა",
    "sickness ავადმყოფობა",
    "accident ავარია",
    "death სიკვდილი",
    "grief მწუხარება",
    "poison შხამი",
    "stink აყროლება",
    "assault თავდასხმა",
    "disaster კატასტროფა",
    "hatred სიძულვილი",
    "pollute დაბინძურება",
    "tragedy ტრაგედია",
    "divorce განქორწინება",
    "poverty სიღარიბე",
    "ugly მახინჯი",
    "cancer კიბო",
    "kill მოკვლა",
    "rotten დამპალი",
    "vomit პირღებინება",
    "agony ტანჯვა",
    "prison ციხე"
  ],
  "math": [
    "math მათემატიკა",
    "algebra ალგებრა",
    "geometry გეომეტრია",
    "calculus გამოთვლა",
    "equation განტოლება",
    "computation გამოთვლა",
    "number რიცხვი",
    "addition დამატება"
  ],
  "arts": [
    "poetry პოეზია",
    "art ხელოვნება",
    "dance ცეკვა",
    "literature ლიტერატურა",
    "novel რომანი",
    "symphony სიმფონია",
    "drama დრამა",
    "sculpture ქანდაკება"
  ],
  "science": [
    "science მეცნიერება",
    "technology ტექნოლოგია",
    "physics ფიზიკა",
    "chemistry ქიმია",
    "Einstein აინშტაინი",
    "NASA ნასა",
    "experiment ექსპერიმენტი",
    "astronomy ასტრონომია"
  ],
  "mental_disease": [
    "sad მოწყენილი",
    "hopeless უიმედო",
    "gloomy პირქუში",
    "tearful ცრემლიანი",
    "miserable უბედური",
    "depressed დეპრესიული"
  ],
  "physical_disease": [
    "sick ავადმყოფი",
    "illness დაავადება",
    "influenza გრიპი",
    "disease ავადმოყოფობა",
    "virus ვირუსი",
    "cancer კიბო"
  ],
  "career": [
    "აღმასრულებელი",
    "მენეჯმენტი",
    "პროფესიონალი",
    "კორპორაცია",
    "ხელფასი",
    "ოფისი",
    "ბიზნესი",
    "კარიერა"
  ],
  "family": [
    "სახლი",
    "მშობლები",
    "შვილები",
    "ოჯახი",
    "ბიძაშვილები",
    "ქორწინება",
    "ქორწილი",
    "ნათესავები"
  ],
  "male_terms": [
    "მამრობითი",
    "კაცი",
    "ბიჭი",
    "ძმაო",
    "ვაჟიშვილი",
    "მამა",
    "ბიძა"
  ],
  "female_terms": [
    "დედრობითი",
    "ქალი",
    "გოგო",
    "და",
    "ქალიშვილი",
    "დედა",
    "დეიდა"
  ],
  "male_names": [
    "გიორგი",
    "დავით",
    "ალექსანდრე",
    "ლუკა",
    "ნიკოლოზ",
    "ირაკლი",
    "ზურაბ",
    "ლევან",
    "საბა",
    "დავითი",
    "ლაშა",
    "ნიკა",
    "გოჩა",
    "მამუკა",
    "ზაზა",
    "მიხეილ",
    "ანდრია",
    "გელა",
    "ნიკოლოზი",
    "ავთანდილ"
  ],
  "female_names": [
    "ნინო",
    "მარიამ",
    "თამარ",
    "ანა",
    "მაია",
    "მარიამი",
    "ნანა",
    "ნათია",
    "ელენე",
    "მანანა",
    "ქეთევან",
    "თამარი",
    "ნათელა",
    "მარინე",
    "სალომე",
    "ხათუნა",
    "მარინა",
    "ეკატერინე",
    "ლია",
    "ლალი"
  ],
  "professions_Bommasani": [
    "ბუღალტერი",
    "მსახიობი",
    "ადმინისტრატორი",
    "ავანტიურისტი",
    "თანაშემწე",
    "ალდერმანი",
    "ელჩი",
    "ანალიტიკოსი",
    "ანთროპოლოგი",
    "არქეოლოგი",
    "მთავარეპისკოპოსი",
    "არქიტექტორი",
    "ხელოვანი",
    "მკვლელი",
    "ასტრონავტი",
    "ასტრონომი",
    "ათლეტი",
    "ავტორი",
    "მცხობელი",
    "ბალერინა",
    "ბანკირი",
    "დალაქი",
    "ბარონი",
    "ბარმენი",
    "ბიოლოგი",
    "ეპისკოპოსი",
    "მცველი",
    "ბუღალტრული",
    "ბოსი",
    "მოკრივე",
    "მაუწყებელი",
    "ბროკერი",
    "ბიუროკრატი",
    "ბიზნესმენი",
    "ჯალათი",
    "კაბი",
    "ოპერატორი",
    "კამპანიელი",
    "კაპიტანი",
    "კარდიოლოგი",
    "მზრუნველი",
    "დურგალი",
    "კარიკატურისტი",
    "ვიოლონჩელისტი",
    "კანცლერი",
    "კაპელანი",
    "შეფ-მზარეული",
    "ქიმიკოსი",
    "ქორეოგრაფი",
    "მოქალაქე",
    "პირი",
    "კლერკი",
    "მწვრთნელი",
    "კოლექციონერი",
    "პოლკოვნიკი",
    "მიმომხილველი",
    "კომიკოსი",
    "მეთაური",
    "კომენტატორი",
    "კომისარი",
    "კომპოზიტორი",
    "კონდუქტორი",
    "კონგრესმენი",
    "კონსულტანტი",
    "კორესპოდენტი",
    "წევრი",
    "მრჩეველი",
    "კრიტიკოსი",
    "თაღლითი",
    "ჯვაროსანი",
    "კურატორი",
    "მეურვე",
    "მოცეკვავე",
    "დეკანოზი",
    "სტომატოლოგი",
    "მოადგილე",
    "დერმატოლოგი",
    "დეტექტივი",
    "დიპლომატი",
    "რეჟისორი",
    "ექიმი",
    "დრამერი",
    "ეკონომისტი",
    "რედაქტორი",
    "აღმზრდელი",
    "ელექტრიკოსი",
    "თანამშრომელი",
    "გარემოსდამცველი",
    "დესპანი",
    "ეპიდემიოლოგი",
    "მახარებელი",
    "ფერმერი",
    "კინორეჟისორი",
    "ფინანსისტი",
    "მეხანძრე",
    "მეთევზე",
    "ფეხბურთელი",
    "ოსტატი",
    "ყაჩაღური",
    "მებაღე",
    "გეოლოგი",
    "მეკარე",
    "გიტარისტი",
    "პარიკმახერი",
    "ხელოსანი",
    "დირექტორი",
    "ისტორიკოსი",
    "დიასახლისი",
    "ილუსტრატორი",
    "მრეწველი",
    "ინსპექტორი",
    "ინსტრუქტორი",
    "გამომგონებელი",
    "გამომძიებელი",
    "დამლაგებელი",
    "იუველირი",
    "ჟურნალისტი",
    "მოსამართლე",
    "იურისტი",
    "მშრომელი",
    "მემამულე",
    "დეპუტატი",
    "ადვოკატი",
    "ლექტორი",
    "ბიბლიოთეკარი",
    "ლეიტენანტი",
    "მაშველი",
    "ლექსისტი",
    "ჯადოქარი",
    "მაგისტრატი",
    "მენეჯერი",
    "მარშალი",
    "მათემატიკოსი",
    "მექანიკოსი",
    "მედიატორი",
    "მინისტრი",
    "მისიონერი",
    "მაფიოზი",
    "ბერი",
    "მუსიკოსი",
    "მთხრობელი",
    "ნატურალისტი",
    "მოლაპარაკე",
    "ნევროლოგი",
    "ნეიროქირურგი",
    "ნოველისტი",
    "მედდა",
    "დამკვირვებელი",
    "ოფიცერი",
    "ორგანისტი",
    "მხატვარი",
    "პარლამენტარი",
    "პასტორი",
    "პათოლოგი",
    "პატრული",
    "პედიატრი",
    "შემსრულებელი",
    "ფარმაცევტი",
    "ქველმოქმედი",
    "ფილოსოფოსი",
    "ფოტოგრაფი",
    "ფოტოჟურნალისტი",
    "ფიზიკოსი",
    "პიანისტი",
    "დამგეგმავი",
    "დრამატურგი",
    "სანტექნიკოსი",
    "პოეტი",
    "პოლიციელი",
    "პოლიტიკოსი",
    "მქადაგებელი",
    "პრეზიდენტი",
    "მღვდელი",
    "პატიმარი",
    "პროფესორი",
    "პროგრამისტი",
    "პრომოუტერი",
    "პროკურორი",
    "გმირი",
    "პროტეჟე",
    "მომიტინგე",
    "ფსიქიატრი",
    "ფსიქოლოგი",
    "პუბლიცისტი",
    "რენტგენოლოგი",
    "რეინჯერი",
    "რეალტორი",
    "მიმღები",
    "მკვლევარი",
    "მეზღვაური",
    "წმინდანი",
    "გამყიდველი",
    "საქსოფონისტი",
    "სწავლული",
    "მეცნიერი",
    "სცენარისტი",
    "მოქანდაკე",
    "მდივანი",
    "სენატორი",
    "სერჟანტი",
    "მსახური",
    "მეწარმე",
    "მომღერალი",
    "კაპიტანი",
    "სოციოლოგი",
    "ჯარისკაცი",
    "სოლისტი",
    "სპორტსმენი",
    "მოღვაწე",
    "ბროკერი",
    "სტრატეგი",
    "სტუდენტი",
    "სტილისტი",
    "ზედამხედველი",
    "ქირურგი",
    "გეოდეზი",
    "მასწავლებელი",
    "ტექნიკოსი",
    "თერაპევტი",
    "ვაჭარი",
    "ხაზინადარი",
    "საყვირი",
    "რეპეტიტორი",
    "მოადგილე",
    "ვალედიქტორიანი",
    "მევიოლინე",
    "ვოკალისტი",
    "მიმტანი",
    "მეურვე",
    "მეომარი",
    "შემდუღებელი",
    "მუშა",
    "მოჭიდავე",
    "მწერალი" 
  ]
}